researchflow/__init__.py
researchflow-0.0.0.dist-info/LICENSE.txt
researchflow-0.0.0.dist-info/METADATA
researchflow-0.0.0.dist-info/WHEEL
researchflow-0.0.0.dist-info/top_level.txt
researchflow-0.0.0.dist-info/RECORD
