Metadata-Version: 2.1
Name: researchflow
Version: 0.0.0
Summary: TensorFlow wrapper and tools for ML research
Home-page: https://github.com/danielwatson6/researchflow
Author: Daniel Watson
Author-email: daniel.watson@nyu.edu
License: MIT
Platform: UNKNOWN
